physlib/__init__.py
physlib/dynamics.py
physlib/electromagnetism.py
physlib/gravitation.py
physlib/kinematics.py
physlib/momentum.py
physlib/optics.py
physlib/rotational_motion.py
physlib/thermodynamics.py
physlib/waves.py
physlib/work_energy.py
physlib-0.1.dist-info/licenses/LICENSE
physlib-0.1.dist-info/METADATA
physlib-0.1.dist-info/WHEEL
physlib-0.1.dist-info/top_level.txt
physlib-0.1.dist-info/RECORD
