Metadata-Version: 2.4
Name: physlib
Version: 0.1
Summary: A simple modular physics library for mechanics, thermodynamics, optics, and more.
Author: Mocha
Author-email: ohplot@gmail.com
License: MIT
Keywords: physics kinematics dynamics waves electricity optics
Classifier: Programming Language :: Python :: 3
Classifier: License :: OSI Approved :: MIT License
Classifier: Operating System :: OS Independent
Classifier: Intended Audience :: Education
Classifier: Topic :: Scientific/Engineering :: Physics
Requires-Python: >=3.6
License-File: LICENSE
Dynamic: author
Dynamic: author-email
Dynamic: classifier
Dynamic: keywords
Dynamic: license
Dynamic: license-file
Dynamic: requires-python
Dynamic: summary
